include/nanoarrow/nanoarrow_types.h
include/nanoarrow/nanoarrow_config.h
include/nanoarrow/array_inline.h
include/nanoarrow/nanoarrow.h
include/nanoarrow/buffer_inline.h
include/nanoarrow/integration/c_data_integration.h
nanopandas/array_types.hpp
nanopandas/nanopandas_ext.cpython-310-x86_64-linux-gnu.so
nanopandas/nanopandas_ext.cpp
nanopandas/CMakeLists.txt
nanopandas/algorithms.hpp
nanopandas/__init__.py
nanopandas/algorithms/generic.cpp
nanopandas/algorithms/generic.hpp
nanopandas/algorithms/string_.hpp
nanopandas/algorithms/numeric.hpp
nanopandas/algorithms/string_.cpp
lib/libnanoarrow.a
nanopandas-0.0.dev1.dist-info/METADATA
nanopandas-0.0.dev1.dist-info/WHEEL
nanopandas-0.0.dev1.dist-info/RECORD
nanopandas-0.0.dev1.dist-info/entry_points.txt
nanopandas-0.0.dev1.dist-info/licenses/LICENSE
