Metadata-Version: 2.1
Name: nanopandas
Version: 0.0.dev1
Summary: Nano implementation of pandas arrays
Author-Email: Will Ayd <william.ayd@icloud.com>
License: BSD 3-Clause License
Classifier: Intended Audience :: Developers
Classifier: Programming Language :: Python :: 3.9
Classifier: Programming Language :: Python :: 3.10
Classifier: Programming Language :: Python :: 3.11
Classifier: Programming Language :: Python :: 3.12
Project-URL: Source, https://github.com/willayd/nanopandas
Requires-Python: >=3.9
License-File: LICENSE
